YiqiXueNodeJs/README.md
YiqiXueNodeJs/__init__.py
YiqiXueNodeJs/__main__.py
YiqiXueNodeJs/file.epub
YiqiXueNodeJs/index.html
YiqiXueNodeJs/css/__init__.py
YiqiXueNodeJs/css/annotations.css
YiqiXueNodeJs/css/main.css
YiqiXueNodeJs/css/normalize.css
YiqiXueNodeJs/css/popup.css
YiqiXueNodeJs/font/__init__.py
YiqiXueNodeJs/font/fontello.eot
YiqiXueNodeJs/font/fontello.svg
YiqiXueNodeJs/font/fontello.ttf
YiqiXueNodeJs/font/fontello.woff
YiqiXueNodeJs/img/__init__.py
YiqiXueNodeJs/img/annotator-glyph-sprite.png
YiqiXueNodeJs/img/annotator-icon-sprite.png
YiqiXueNodeJs/img/apple-touch-icon.png
YiqiXueNodeJs/img/cancelfullscreen.png
YiqiXueNodeJs/img/close.png
YiqiXueNodeJs/img/fullscreen.png
YiqiXueNodeJs/img/loader.gif
YiqiXueNodeJs/img/menu-icon.png
YiqiXueNodeJs/img/save.png
YiqiXueNodeJs/img/saved.png
YiqiXueNodeJs/img/settings-s.png
YiqiXueNodeJs/img/settings.png
YiqiXueNodeJs/img/star.png
YiqiXueNodeJs/js/__init__.py
YiqiXueNodeJs/js/epub.js
YiqiXueNodeJs/js/epub.min.js
YiqiXueNodeJs/js/epub.min.map
YiqiXueNodeJs/js/hooks.min.js
YiqiXueNodeJs/js/hooks.min.map
YiqiXueNodeJs/js/reader.js
YiqiXueNodeJs/js/reader.js.map
YiqiXueNodeJs/js/reader.min.js
YiqiXueNodeJs/js/reader.min.map
YiqiXueNodeJs/js/hooks/__init__.py
YiqiXueNodeJs/js/hooks/extensions/__init__.py
YiqiXueNodeJs/js/hooks/extensions/highlight.js
YiqiXueNodeJs/js/libs/__init__.py
YiqiXueNodeJs/js/libs/jquery.min.js
YiqiXueNodeJs/js/libs/localforage.min.js
YiqiXueNodeJs/js/libs/screenfull.js
YiqiXueNodeJs/js/libs/screenfull.min.js
YiqiXueNodeJs/js/libs/zip.min.js
YiqiXueNodeJs/js/plugins/__init__.py
YiqiXueNodeJs/js/plugins/hypothesis.js
YiqiXueNodeJs/js/plugins/search.js
yiqi_xue_node_js-2024.3.2.0.dist-info/METADATA
yiqi_xue_node_js-2024.3.2.0.dist-info/WHEEL
yiqi_xue_node_js-2024.3.2.0.dist-info/entry_points.txt
yiqi_xue_node_js-2024.3.2.0.dist-info/top_level.txt
yiqi_xue_node_js-2024.3.2.0.dist-info/RECORD
